UnleashClient/__init__.py
UnleashClient/cache.py
UnleashClient/constants.py
UnleashClient/environment_resolver.py
UnleashClient/events.py
UnleashClient/impact_metrics.py
UnleashClient/py.typed
UnleashClient/utils.py
UnleashClient/api/__init__.py
UnleashClient/api/features.py
UnleashClient/api/metrics.py
UnleashClient/api/register.py
UnleashClient/connectors/__init__.py
UnleashClient/connectors/base_connector.py
UnleashClient/connectors/bootstrap_connector.py
UnleashClient/connectors/offline_connector.py
UnleashClient/connectors/polling_connector.py
UnleashClient/connectors/streaming_connector.py
UnleashClient/periodic_tasks/__init__.py
UnleashClient/periodic_tasks/send_metrics.py
docs/Makefile
docs/basecache.rst
docs/celery.rst
docs/changelog.rst
docs/conf.py
docs/customcache.rst
docs/customstrategies.rst
docs/development.rst
docs/eventcallbacks.rst
docs/events.rst
docs/filecache.rst
docs/index.rst
docs/installation.rst
docs/make.bat
docs/strategy.rst
docs/unleashclient.rst
docs/usage.rst
docs/wsgi.rst
scripts/get-spec.sh
unleashclient-6.5.1.dist-info/licenses/LICENSE.md
unleashclient-6.5.1.dist-info/METADATA
unleashclient-6.5.1.dist-info/WHEEL
unleashclient-6.5.1.dist-info/top_level.txt
unleashclient-6.5.1.dist-info/RECORD
