Metadata-Version: 2.4
Name: UnleashClient
Version: 6.5.1
Summary: Python client for the Unleash feature toggle system!
Author-email: Ivan Lee <ivanklee86@gmail.com>
Project-URL: Homepage, https://github.com/Unleash/unleash-python-sdk
Project-URL: Documentation, https://docs.getunleash.io/unleash-python-sdk
Project-URL: Changelog, https://github.com/unleash/unleash-python-sdk/blob/main/CHANGELOG.md
Project-URL: Repository, https://github.com/Unleash/unleash-python-sdk
Project-URL: Issues, https://github.com/Unleash/unleash-python-sdk/issues
Classifier: Development Status :: 5 - Production/Stable
Classifier: Intended Audience :: Developers
Classifier: License :: OSI Approved :: MIT License
Classifier: Typing :: Typed
Classifier: Programming Language :: Python :: 3.8
Classifier: Programming Language :: Python :: 3.9
Classifier: Programming Language :: Python :: 3.10
Classifier: Programming Language :: Python :: 3.11
Classifier: Programming Language :: Python :: 3.12
Classifier: Programming Language :: Python :: 3.13
Requires-Python: >=3.8
License-File: LICENSE.md
Requires-Dist: requests
Requires-Dist: fcache
Requires-Dist: mmh3
Requires-Dist: apscheduler<4.0.0
Requires-Dist: importlib_metadata
Requires-Dist: python-dateutil
Requires-Dist: semver<4.0.0
Requires-Dist: yggdrasil-engine>=1.0.0
Requires-Dist: launchdarkly-eventsource
Dynamic: license-file
